README.rst
setup.py
rundeck/__init__.py
rundeck/api.py
rundeck/client.py
rundeck/connection.py
rundeck/defaults.py
rundeck/exceptions.py
rundeck/transforms.py
rundeck/util.py
rundeckrun.egg-info/PKG-INFO
rundeckrun.egg-info/SOURCES.txt
rundeckrun.egg-info/dependency_links.txt
rundeckrun.egg-info/requires.txt
rundeckrun.egg-info/top_level.txt
tests/__init__.py
tests/test_api.py
tests/test_client.py
tests/test_connection.py