Metadata-Version: 1.1
Name: rundeckrun
Version: 0.1.10
Summary: Rundeck API Python client
Home-page: https://github.com/marklap/rundeckrun
Author: rundeckrun@mindmind.com
Author-email: rundeckrun@mindmind.com
License: http://creativecommons.org/licenses/by-sa/3.0/
Platform: UNKNOWN
Classifier: Development Status :: 4 - Beta
Classifier: Intended Audience :: Developers
Classifier: Intended Audience :: Information Technology
Classifier: Intended Audience :: System Administrators
Classifier: Operating System :: OS Independent
Classifier: Programming Language :: Python :: 2.7
Classifier: Programming Language :: Python :: 3.3
Classifier: Topic :: System :: Software Distribution
Classifier: Topic :: System :: Systems Administration
Classifier: Topic :: Utilities
